setup.py
prog5/__init__.py
prog5/prog5.py
prog5.egg-info/PKG-INFO
prog5.egg-info/SOURCES.txt
prog5.egg-info/dependency_links.txt
prog5.egg-info/top_level.txt