Metadata-Version: 2.1
Name: prog5
Version: 0.0.1
Summary: Prog5
Home-page: UNKNOWN
Author: Tester
Author-email: <bolawa1518@dmonies.com>
License: UNKNOWN
Keywords: python,program,vtu,sce
Platform: UNKNOWN
Classifier: Development Status :: 1 - Planning
Classifier: Intended Audience :: Developers
Classifier: Programming Language :: Python :: 3
Classifier: Operating System :: Unix
Classifier: Operating System :: MacOS :: MacOS X
Classifier: Operating System :: Microsoft :: Windows
